odoo9_addon_event_track_location_overlap-9.0.1.0.0.99.dev3-nspkg.pth
odoo_addons/event_track_location_overlap/README.rst
odoo_addons/event_track_location_overlap/__init__.py
odoo_addons/event_track_location_overlap/__openerp__.py
odoo_addons/event_track_location_overlap/i18n/es.po
odoo_addons/event_track_location_overlap/i18n/event_track_location_overlap.pot
odoo_addons/event_track_location_overlap/models/__init__.py
odoo_addons/event_track_location_overlap/models/event_track.py
odoo_addons/event_track_location_overlap/models/event_track_location.py
odoo_addons/event_track_location_overlap/static/description/icon.png
odoo_addons/event_track_location_overlap/tests/__init__.py
odoo_addons/event_track_location_overlap/tests/test_overlap.py
odoo_addons/event_track_location_overlap/views/event_track_location_view.xml
odoo9_addon_event_track_location_overlap-9.0.1.0.0.99.dev3.dist-info/METADATA
odoo9_addon_event_track_location_overlap-9.0.1.0.0.99.dev3.dist-info/WHEEL
odoo9_addon_event_track_location_overlap-9.0.1.0.0.99.dev3.dist-info/namespace_packages.txt
odoo9_addon_event_track_location_overlap-9.0.1.0.0.99.dev3.dist-info/top_level.txt
odoo9_addon_event_track_location_overlap-9.0.1.0.0.99.dev3.dist-info/RECORD
